devices/__init__.py
devices/devices.py
devices/zlg/__init__.py
devices/zlg/main.py
devices/zlg/zlgcan.py
devices/zlg/zlgcan_demo.py
framework/__init__.py
framework/canbox.py
framework/canbus.py
framework/candb.py
framework/canfactory.py
framework/canmsg.py
framework/cansignal.py
framework/concurrentcanbox.py
framework/glue.py
framework/nodes.py
framework/trigger.py
can_box_chw-0.0.3.dist-info/LICENSE
can_box_chw-0.0.3.dist-info/METADATA
can_box_chw-0.0.3.dist-info/WHEEL
can_box_chw-0.0.3.dist-info/top_level.txt
can_box_chw-0.0.3.dist-info/RECORD
